LICENSE
README.md
setup.cfg
setup.py
tnzapi/__init__.py
tnzapi/_config.py
tnzapi.egg-info/PKG-INFO
tnzapi.egg-info/SOURCES.txt
tnzapi.egg-info/dependency_links.txt
tnzapi.egg-info/not-zip-safe
tnzapi.egg-info/requires.txt
tnzapi.egg-info/top_level.txt
tnzapi/api/__init__.py
tnzapi/api/actions/__init__.py
tnzapi/api/actions/dtos/__init__.py
tnzapi/api/actions/dtos/action_api_result_dto.py
tnzapi/api/actions/requests/__init__.py
tnzapi/api/actions/requests/_common.py
tnzapi/api/actions/requests/abort.py
tnzapi/api/actions/requests/pacing.py
tnzapi/api/actions/requests/reschedule.py
tnzapi/api/actions/requests/resubmit.py
tnzapi/api/actions/responses/__init__.py
tnzapi/api/actions/responses/action_api_result.py
tnzapi/api/addressbook/__init__.py
tnzapi/api/addressbook/contactgroups/__init__.py
tnzapi/api/addressbook/contactgroups/dtos/__init__.py
tnzapi/api/addressbook/contactgroups/dtos/contact_group_api_create_request_dto.py
tnzapi/api/addressbook/contactgroups/dtos/contact_group_api_result_dto.py
tnzapi/api/addressbook/contactgroups/dtos/contact_group_list_api_result_dto.py
tnzapi/api/addressbook/contactgroups/requests/__init__.py
tnzapi/api/addressbook/contactgroups/requests/_common.py
tnzapi/api/addressbook/contactgroups/requests/create.py
tnzapi/api/addressbook/contactgroups/requests/delete.py
tnzapi/api/addressbook/contactgroups/requests/detail.py
tnzapi/api/addressbook/contactgroups/requests/list.py
tnzapi/api/addressbook/contactgroups/responses/__init__.py
tnzapi/api/addressbook/contactgroups/responses/contact_group_api_result.py
tnzapi/api/addressbook/contactgroups/responses/contact_group_list_api_result.py
tnzapi/api/addressbook/contacts/__init__.py
tnzapi/api/addressbook/contacts/dtos/__init__.py
tnzapi/api/addressbook/contacts/dtos/contact_api_result_dto.py
tnzapi/api/addressbook/contacts/dtos/contact_list_api_result_dto.py
tnzapi/api/addressbook/contacts/dtos/contact_model.py
tnzapi/api/addressbook/contacts/dtos/contact_search_request_dto.py
tnzapi/api/addressbook/contacts/requests/__init__.py
tnzapi/api/addressbook/contacts/requests/_common.py
tnzapi/api/addressbook/contacts/requests/create.py
